ai_functions/__init__.py
ai_functions/functions.py
ai_functions-0.4.3.dist-info/METADATA
ai_functions-0.4.3.dist-info/WHEEL
ai_functions-0.4.3.dist-info/RECORD
