Metadata-Version: 2.1
Name: ai-functions
Version: 0.4.3
Summary: manage openai functions and execution
License: MIT
Author: erik aronesty
Author-email: erik@q32.com
Requires-Python: >=3.9,<4.0
Classifier: License :: OSI Approved :: MIT License
Classifier: Programming Language :: Python :: 3
Classifier: Programming Language :: Python :: 3.9
Classifier: Programming Language :: Python :: 3.10
Classifier: Programming Language :: Python :: 3.11
